cuipyd/__init__.py
cuipyd/ipane.py
cuipyd/logging.py
cuipyd/main_window.py
cuipyd/mouse.py
cuipyd/pane.py
cuipyd/threads.py
cuipyd/tuples.py
cuipyd/colors/color_scheme.py
cuipyd/colors/colors.py
cuipyd/layouts/__init__.py
cuipyd/layouts/directional_layout.py
cuipyd/layouts/layout.py
cuipyd/layouts/tab_layout.py
cuipyd/popups/__init__.py
cuipyd/popups/popup.py
cuipyd/popups/text_popup.py
cuipyd/tests/bouncy_ball_test.py
cuipyd/tests/layout_test.py
cuipyd/tests/tab_test.py
cuipyd/tests/widget_test.py
cuipyd/utils/__init__.py
cuipyd/utils/direction.py
cuipyd/utils/general.py
cuipyd/widgets/__init__.py
cuipyd/widgets/base_widget.py
cuipyd/widgets/button.py
cuipyd/widgets/scrollview.py
cuipyd/widgets/spreadsheet.py
cuipyd-0.0.10.dist-info/LICENSE
cuipyd-0.0.10.dist-info/WHEEL
cuipyd-0.0.10.dist-info/METADATA
cuipyd-0.0.10.dist-info/RECORD
