Metadata-Version: 2.1
Name: cuipyd
Version: 0.0.10
Summary: A Python library for creating Terminal UIs
Author-email: Charlie Dudzik <dudzikc@outlook.com>
Classifier: License :: OSI Approved :: MIT License
